README.md
setup.py
infinite_image_downloader/__init__.py
infinite_image_downloader/infinite_image_downloader.py
infinite_image_downloader.egg-info/PKG-INFO
infinite_image_downloader.egg-info/SOURCES.txt
infinite_image_downloader.egg-info/dependency_links.txt
infinite_image_downloader.egg-info/entry_points.txt
infinite_image_downloader.egg-info/requires.txt
infinite_image_downloader.egg-info/top_level.txt